{ 
    "buru_7": [
    {
        "specialty": "母乳喂养",
        "recommand": "推荐摄入",
        "dish": "面汤"
    },
    {
        "specialty": "母乳喂养",
        "recommand": "推荐摄入",
        "dish": "米汤"
    },
    {
        "specialty": "母乳喂养",
        "recommand": "推荐摄入",
        "dish": "猪蹄汤"
    },
    {
        "specialty": "母乳喂养",
        "recommand": "推荐摄入",
        "dish": "排骨汤"
    },
    {
        "specialty": "母乳喂养",
        "recommand": "推荐摄入",
        "dish": "菜汤"
    },
    {
        "specialty": "母乳喂养",
        "recommand": "推荐摄入",
        "dish": "豆腐汤"
    },
    {
        "specialty": "母乳喂养",
        "recommand": "推荐摄入",
        "dish": "猪腿煮汤"
    },
    {
        "specialty": "母乳喂养",
        "recommand": "推荐摄入",
        "dish": "猪排骨煮汤"
    },
    {
        "specialty": "母乳喂养",
        "recommand": "推荐摄入",
        "dish": "猪尾煮汤"
    },
    {
        "specialty": "母乳喂养",
        "recommand": "推荐摄入",
        "dish": "鲫鱼汤"
    },
    {
        "specialty": "母乳喂养",
        "recommand": "推荐摄入",
        "dish": "猪尾煮汤"
    },
    {
        "specialty": "母乳喂养",
        "recommand": "推荐摄入",
        "dish": "黄花菜鸡汤"
    },
    {
        "specialty": "母乳喂养",
        "recommand": "推荐摄入",
        "dish": "鸡蛋煮汤"
    },
    {
        "specialty": "母乳喂养",
        "recommand": "推荐摄入",
        "dish": "鸡蛋面"
    },
    {
        "specialty": "母乳喂养",
        "recommand": "推荐摄入",
        "dish": "黄豆排骨汤"
    },
    {
        "specialty": "母乳喂养",
        "recommand": "推荐摄入",
        "dish": "清炒西兰花"
    },
    {
        "specialty": "母乳喂养",
        "recommand": "推荐摄入",
        "dish": "鲫鱼汤"
    },
    {
        "specialty": "母乳喂养",
        "recommand": "推荐摄入",
        "dish": "芹菜炒肉丝"
    },
    {
        "specialty": "母乳喂养",
        "recommand": "推荐摄入",
        "dish": "素炒大白菜"
    },
    {
        "specialty": "母乳喂养",
        "recommand": "推荐摄入",
        "dish": "红糖煮蛋"
    }
]}